{
  "news": [
    {
      "category": "release",
      "code": "101977",
      "title": "乃木坂46 42ndシングル 7月22日(水)に発売決定！",
      "caption": "",
      "link": "https://www.nogizaka46.com/s/n46/news/detail/101977",
      "pubdate": "2026/06/01 00:45:00",
      "thumbnail": null,
      "content": "乃木坂46 42ndシングルを2026年7月22日(水)に発売することが決定いたしました！<br /><br />6月7日(日)の深夜に放送されるテレビ東京系「乃木坂工事中」にて、42ndシングルの選抜メンバーを発表いたします。<br /><br />今後も、42ndシングルに関連する様々な情報をお届けいたしますので、ぜひチェックしてみてください！<br /><br /><br />■最新リリース情報<br />乃木坂46 42ndシングル<br />発売日：2026年7月22日(水)<br /><br />-CDショップでの予約はコチラ-<br /><a href=\"http://nogizaka46.lnk.to/20260722_42ndSingle_CD\" target=\"_blank\">http://nogizaka46.lnk.to/20260722_42ndSingle_CD</a><br />※6月1日(月)AM10時より予約受付スタート<br /><br />【Blu-ray付き】<br />初回仕様限定盤TYPE-A / SRCL-13790～13791 / 2,000(tax in)<br />初回仕様限定盤TYPE-B / SRCL-13792～13793 / 2,000(tax in)<br />初回仕様限定盤TYPE-C / SRCL-13794～13795 / 2,000(tax in)<br />初回仕様限定盤TYPE-D / SRCL-13796～13797 / 2,000(tax in)<br /> <br />★初回仕様限定盤・封入特典★<br />応募特典シリアルナンバー封入<br />メンバー生写真1枚封入（各TYPE別32種より1枚ランダム封入）<br /><br />【CDのみ】<br />通常盤 / SRCL-13798 / 1,200(tax in)"
    },
    {
      "category": "web",
      "code": "101983",
      "title": "「乃木坂工事中」の最新話「即興芝居ワークショップ」をYouTubeにて公開！【乃木坂配信中】",
      "caption": "",
      "link": "https://www.nogizaka46.com/s/n46/news/detail/101983",
      "pubdate": "2026/06/01 00:44:59",
      "thumbnail": null,
      "content": "公式YouTubeチャンネル「乃木坂配信中」にて、2026年5月31日にオンエアされました「乃木坂工事中」の最新話<br />・即興芝居ワークショップ<br />を公開いたしました！<br /><br />今回の乃木坂工事中は「即興芝居ワークショップ」を開催！<br />お題の設定とセリフとオチが与えられた中でメンバーが即興芝居に挑戦！<br />超ハイレベルなエチュードにメンバー大混乱！<br />さらに名探偵増田にスタジオ大爆笑！<br /><br />ぜひご覧ください！<br /><br />動画はこちら！<br /><iframe width=\"560\" height=\"315\" src=\"https://www.youtube.com/embed/REPiqqFJcCo?si=HzfwPZPMEdy-IiP1\" title=\"YouTube video player\" frameborder=\"0\" allow=\"accelerometer; autoplay; clipboard-write; encrypted-media; gyroscope; picture-in-picture; web-share\" referrerpolicy=\"strict-origin-when-cross-origin\" allowfullscreen=\"allowfullscreen\"></iframe><br /><a href=\"https://youtu.be/REPiqqFJcCo\" target=\"_blank\">https://youtu.be/REPiqqFJcCo</a><br /><br />チャンネル登録もよろしくお願いします！<br /><a href=\"https://www.youtube.com/c/nogizakahaishinchu\" target=\"_blank\">https://www.youtube.com/c/nogizakahaishinchu</a>"
    },
    {
      "category": "tv",
      "code": "101982",
      "title": "＜次回予告＞「乃木坂工事中」",
      "caption": "",
      "link": "https://www.nogizaka46.com/s/n46/news/detail/101982",
      "pubdate": "2026/06/01 00:44:51",
      "thumbnail": null,
      "content": "<p>次回の乃木坂工事中は&hellip;<br />「因縁相撲2026春場所」が開幕！<br /> <br />ちょっとした不満や因縁をぶつけ合い<br />最後は相撲で決着をつける恒例企画！<br />まさかの名勝負にスタジオ大興奮！<br /><br />-------------------------------------------</p><p>只今、大躍進中の乃木坂46！<br />その活躍は、ライブ、バラエティ、ドラマ、<br />映画、モデルなど多岐にわたる。<br />そんな彼女たちにもっともっと勢いをつけてもらうために<br />この番組ではメンバーの新たな一面や魅力を引き出す<br />さまざまな企画にチャレンジ！！<br />公式お兄ちゃんでもあるバナナマンとともに<br />さらなる飛躍を目指していきます！！<br /><br />放送時間：日曜日深夜24時15分から<br />放送局：テレビ東京、テレビ大阪、テレビ愛知、テレビ北海道、テレビせとうち、TVQ九州放送<br />出演：乃木坂46、ＭＣ：バナナマン<br /><br />そのほかの放送局<br />石川テレビ：毎週月曜24:15～24:48にて放送<br />※10月より毎週水曜放送から毎週月曜放送へ移行<br />琉球朝日放送：毎週土曜24:00～24:30にて放送<br />※10月4日(土)より放送開始</p><p><br />＊特別番組などにより、予告なしに放送時間が変更になることがあります。ご了承ください。<br />＊詳細は各放送局の番組表などをご参照ください。</p><p><img src=\"https://www.nogizaka46.com/files/46/news/26_04_kouzi.jpg\" alt=\"\" width=\"1280\" height=\"720\" /><br /><a href=\"/files/46/_pre/news/img/2021/06/09/nogityuu_2106.jpg\"></a></p>"
    }
  ],
  "count": "3"
}